blemli_mail/__init__.py
blemli_mail/send.py
blemli_mail-0.0.20.dist-info/METADATA
blemli_mail-0.0.20.dist-info/WHEEL
blemli_mail-0.0.20.dist-info/licenses/LICENSE
blemli_mail-0.0.20.dist-info/RECORD
